napalm_control/Lie_tools.py
napalm_control/__init__.py
napalm_control/approximation_tools.py
napalm_control/shuffle_tools.py
napalm_control/fliess/lie_basis.pickle
napalm_control/fliess/moments_grading.pickle
napalm_control/nonlinear_moments/lie_basis.pickle
napalm_control/nonlinear_moments/moments_grading.pickle
napalm_control-0.0.6.dist-info/LICENSE
napalm_control-0.0.6.dist-info/METADATA
napalm_control-0.0.6.dist-info/WHEEL
napalm_control-0.0.6.dist-info/top_level.txt
napalm_control-0.0.6.dist-info/RECORD
