Metadata-Version: 2.1
Name: napalm-control
Version: 0.0.6
Summary: Nonlinear Algebraic Approximation in Control systems
Home-page: https://github.com/ViktorRusakov/napalm-control
Author: Viktor Rusakov
Author-email: vrusakov66@gmail.com
License: UNKNOWN
Platform: UNKNOWN
Classifier: Programming Language :: Python :: 3
Classifier: License :: OSI Approved :: MIT License
Classifier: Operating System :: OS Independent
Requires-Python: >=3.6
